[
	{
		"title": "Apple Watch SE, 40 мм, корпус из алюминия, спортивный ремешок (сияющая звезда)",
		"href": "https://www.c-store.ru/apple/watch",
		"prices": [
			24
		],
		"description": "",
		"domain": "www.c-store.ru",
		"type": "site"
	},
	{
		"title": "Apple Watch SE, 44 мм, корпус из алюминия, спортивный ремешок (темная ночь)",
		"href": "https://www.c-store.ru/apple/watch",
		"prices": [
			27
		],
		"description": "",
		"domain": "www.c-store.ru",
		"type": "site"
	},
	{
		"title": "Apple Watch Series 7, 41 мм, корпус из алюминия, спортивный ремешок (сияющая звезда)",
		"href": "https://www.c-store.ru/apple/watch",
		"prices": [
			36
		],
		"description": "",
		"domain": "www.c-store.ru",
		"type": "site"
	},
	{
		"title": "Apple Watch Series 7, 45 мм, корпус из алюминия, спортивный ремешок (темная ночь)",
		"href": "https://www.c-store.ru/apple/watch",
		"prices": [
			39
		],
		"description": "",
		"domain": "www.c-store.ru",
		"type": "site"
	},
	{
		"title": "Apple Watch Series 3, 38 мм, корпус из алюминия, спортивный ремешок (серебристый)",
		"href": "https://www.c-store.ru/apple/watch",
		"prices": [
			27
		],
		"description": "",
		"domain": "www.c-store.ru",
		"type": "site"
	},
	{
		"title": "Apple Watch Series 3, 42 мм, корпус из алюминия, спортивный ремешок (серый космос)",
		"href": "https://www.c-store.ru/apple/watch",
		"prices": [
			39
		],
		"description": "",
		"domain": "www.c-store.ru",
		"type": "site"
	},
	{
		"title": "Apple Watch SE, 44 мм, корпус из алюминия, спортивный ремешок (серый космос)",
		"href": "https://www.c-store.ru/apple/watch",
		"prices": [
			36
		],
		"description": "",
		"domain": "www.c-store.ru",
		"type": "site"
	},
	{
		"title": "Apple Watch Series 7, 45 мм, корпус из алюминия, спортивный ремешок (сияющая звезда)",
		"href": "https://www.c-store.ru/apple/watch",
		"prices": [
			24
		],
		"description": "",
		"domain": "www.c-store.ru",
		"type": "site"
	},
	{
		"title": "Apple Watch Series 7, 41 мм, корпус из алюминия, спортивный ремешок (зеленый)",
		"href": "https://www.c-store.ru/apple/watch",
		"prices": [
			39
		],
		"description": "",
		"domain": "www.c-store.ru",
		"type": "site"
	},
	{
		"title": "Apple Watch SE, 40 мм, корпус из алюминия, спортивный ремешок (синий омут)",
		"href": "https://www.c-store.ru/apple/watch",
		"prices": [
			39
		],
		"description": "",
		"domain": "www.c-store.ru",
		"type": "site"
	},
	{
		"title": "Apple Watch Series 7, 45 мм, корпус из алюминия, спортивный ремешок (синий)",
		"href": "https://www.c-store.ru/apple/watch",
		"prices": [
			36
		],
		"description": "",
		"domain": "www.c-store.ru",
		"type": "site"
	},
	{
		"title": "Apple Watch Series 7, 45 мм, корпус из алюминия, спортивный ремешок Nike (темная ночь)",
		"href": "https://www.c-store.ru/apple/watch",
		"prices": [
			24
		],
		"description": "",
		"domain": "www.c-store.ru",
		"type": "site"
	},
	{
		"title": "Apple Watch Series 7, 41 мм, корпус из алюминия, спортивный ремешок (темная ночь)",
		"href": "https://www.c-store.ru/apple/watch",
		"prices": [
			36
		],
		"description": "",
		"domain": "www.c-store.ru",
		"type": "site"
	},
	{
		"title": "Apple Watch SE, 40 мм, корпус из алюминия, спортивный ремешок (темная ночь)",
		"href": "https://www.c-store.ru/apple/watch",
		"prices": [
			27
		],
		"description": "",
		"domain": "www.c-store.ru",
		"type": "site"
	},
	{
		"title": "Apple Watch Series 7, 41 мм, корпус из алюминия, спортивный ремешок (синий)",
		"href": "https://www.c-store.ru/apple/watch",
		"prices": [
			36
		],
		"description": "",
		"domain": "www.c-store.ru",
		"type": "site"
	},
	{
		"title": "Apple Watch SE, 44 мм, корпус из алюминия, спортивный ремешок (сияющая звезда)",
		"href": "https://www.c-store.ru/apple/watch",
		"prices": [
			39
		],
		"description": "",
		"domain": "www.c-store.ru",
		"type": "site"
	}
]